pepq/__init__.py
pepq/analysis.py
pepq/io.py
pepq/pepq
pepq/pepq.py
pepq/calibration/__init__.py
pepq/calibration/ad_conformal.py
pepq/data/__init__.py
pepq/data/_get_score.py
pepq/data/build_data.py
pepq/data/config.py
pepq/data/display.py
pepq/data/feature_importance.py
pepq/data/helpers.py
pepq/data/preprocessor.py
pepq/data/steps.py
pepq/eda/__init__.py
pepq/eda/base.py
pepq/eda/importance.py
pepq/eda/pep_eda.py
pepq/metrics/__init__.py
pepq/metrics/_core.py
pepq/metrics/_panels.py
pepq/metrics/metrics.py
pepq/metrics/plot_classification.py
pepq/metrics/plot_regression.py
pepq/model/__init__.py
pepq/model/base.py
pepq/model/classification.py
pepq/model/feature_engineer.py
pepq/model/helpers.py
pepq/model/multi_model.py
pepq/model/regression.py
pepq/model/vis.py
pepq-0.0.1.dist-info/METADATA
pepq-0.0.1.dist-info/WHEEL
pepq-0.0.1.dist-info/RECORD
